LICENSE
MANIFEST.in
README.md
pyproject.toml
setup.py
cupy/__init__.py
cupy/_environment.py
cupy/_util.pyi
cupy/_util.pyx
cupy/_version.py
cupy/cublas.py
cupy/cudnn.py
cupy/cusolver.py
cupy/cusparse.py
cupy/cutensor.py
cupy.egg-info/PKG-INFO
cupy.egg-info/SOURCES.txt
cupy.egg-info/dependency_links.txt
cupy.egg-info/not-zip-safe
cupy.egg-info/requires.txt
cupy.egg-info/top_level.txt
cupy/../cupyx/scipy/ndimage/cuda/LICENSE
cupy/../cupyx/scipy/ndimage/cuda/pba_kernels_2d.h
cupy/../cupyx/scipy/ndimage/cuda/pba_kernels_3d.h
cupy/_binary/__init__.py
cupy/_binary/elementwise.py
cupy/_binary/packing.py
cupy/_core/__init__.pxd
cupy/_core/__init__.py
cupy/_core/_accelerator.pxd
cupy/_core/_accelerator.pyx
cupy/_core/_carray.pxd
cupy/_core/_carray.pyx
cupy/_core/_codeblock.py
cupy/_core/_cub_reduction.pxd
cupy/_core/_cub_reduction.pyx
cupy/_core/_dtype.pxd
cupy/_core/_dtype.pyx
cupy/_core/_fusion_interface.py
cupy/_core/_fusion_kernel.pyx
cupy/_core/_fusion_op.py
cupy/_core/_fusion_optimization.py
cupy/_core/_fusion_thread_local.pyx
cupy/_core/_fusion_trace.pyx
cupy/_core/_fusion_variable.pxd
cupy/_core/_fusion_variable.pyx
cupy/_core/_gufuncs.py
cupy/_core/_kernel.pxd
cupy/_core/_kernel.pyx
cupy/_core/_memory_range.pxd
cupy/_core/_memory_range.pyx
cupy/_core/_optimize_config.pxd
cupy/_core/_optimize_config.pyx
cupy/_core/_reduction.pxd
cupy/_core/_reduction.pyx
cupy/_core/_routines_binary.pxd
cupy/_core/_routines_binary.pyx
cupy/_core/_routines_indexing.pxd
cupy/_core/_routines_indexing.pyx
cupy/_core/_routines_linalg.pxd
cupy/_core/_routines_linalg.pyx
cupy/_core/_routines_logic.pxd
cupy/_core/_routines_logic.pyx
cupy/_core/_routines_manipulation.pxd
cupy/_core/_routines_manipulation.pyx
cupy/_core/_routines_math.pxd
cupy/_core/_routines_math.pyx
cupy/_core/_routines_sorting.pxd
cupy/_core/_routines_sorting.pyx
cupy/_core/_routines_statistics.pxd
cupy/_core/_routines_statistics.pyx
cupy/_core/_scalar.pxd
cupy/_core/_scalar.pyx
cupy/_core/_ufuncs.py
cupy/_core/core.pxd
cupy/_core/core.pyx
cupy/_core/dlpack.pxd
cupy/_core/dlpack.pyx
cupy/_core/flags.pyx
cupy/_core/fusion.pyx
cupy/_core/halffloat.h
cupy/_core/internal.pxd
